setup.py
blupointclient/__init__.py
blupointclient.egg-info/PKG-INFO
blupointclient.egg-info/SOURCES.txt
blupointclient.egg-info/dependency_links.txt
blupointclient.egg-info/requires.txt
blupointclient.egg-info/top_level.txt
blupointclient/cms/__init__.py
blupointclient/cms/content.py
blupointclient/cms/contents.py
blupointclient/cms/search.py
blupointclient/cms/subject.py
blupointclient/cms/subjects.py