Metadata-Version: 1.0
Name: blupointclient
Version: 0.1.14
Summary: BluPoint Client
Home-page: UNKNOWN
Author: UNKNOWN
Author-email: UNKNOWN
License: UNKNOWN
Platform: UNKNOWN
